[
  {
    "id": "proposal-template",
    "title": "Template Proposal Magang",
    "url": "https://example.com/proposal-template",
    "icon": "file",
    "section": "Proposal Magang",
    "preview": {
      "text": "Template dan contoh proposal magang yang bisa digunakan",
      "domain": "example.com"
    }
  },
  {
    "id": "proposal-guideline",
    "title": "Panduan Proposal Magang",
    "url": "https://example.com/proposal-guideline",
    "icon": "book",
    "section": "Proposal Magang",
    "preview": {
      "text": "Panduan lengkap cara membuat proposal magang",
      "domain": "example.com"
    }
  },
  {
    "id": "materi-semester-7",
    "title": "Materi Semester 7",
    "url": "https://example.com/materi",
    "icon": "book",
    "section": "Materi Kuliah",
    "preview": {
      "text": "Kumpulan materi kuliah semester 7",
      "domain": "example.com"
    }
  },
  {
    "id": "github",
    "title": "GitHub",
    "url": "https://github.com/setiadyanwar",
    "icon": "github",
    "section": "Development",
    "preview": {
      "text": "Repository kode dan project yang sedang dikerjakan",
      "domain": "github.com"
    }
  },
  {
    "id": "portfolio",
    "title": "Portfolio Website",
    "url": "https://setiadyanwar.github.io",
    "icon": "globe",
    "section": "Development",
    "preview": {
      "text": "Website portfolio pribadi dengan showcase project dan experience",
      "domain": "setiadyanwar.github.io"
    }
  }
]

